{
  "queue": [
    {
      "id": "1",
      "birth": "1969-04-17",
      "name": "Oslier Oliveira",
      "gender": "masculino",
      "email": "oslier@gmail.com",
      "phone": "+55 (16) 99714-4102",
      "address": "Rua Affonso Botelho de Abreu Sampaio, 638",
      "city": "São Carlos-SP",
      "cep": "13563-307"
    },
    {
      "id": "2",
      "birth": "1991-05-10",
      "name": "Pedro Sousa",
      "gender": "masculino",
      "email": "pedros1991@gmail.com",
      "phone": "+55 (16) 99224-1111",
      "address": "Rua sss ffff, 600",
      "city": "São Carlos-SP",
      "cep": "13560-000"
    },
    {
      "id": "3",
      "birth": "1970-08-19",
      "name": "Xica Bebel",
      "gender": "Feminino",
      "email": "xbevel@gmail.com",
      "phone": "+55 (19) 99222-0022",
      "address": "Rua Sem Nome, 22222",
      "city": "Descalvado-SP",
      "cep": "13690-000"
    }
  ]
}
